arrayer/__init__.py
arrayer/dtype.py
arrayer/exception.py
arrayer/kabsch.py
arrayer/matrix.py
arrayer/pca.py
arrayer/pcloud.py
arrayer/rmsd.py
arrayer/tensor.py
arrayer/typing.py
arrayer-0.0.6.dist-info/METADATA
arrayer-0.0.6.dist-info/WHEEL
arrayer-0.0.6.dist-info/top_level.txt
arrayer-0.0.6.dist-info/RECORD
